<annotation>
	<folder>plates</folder>
	<filename>18.jpg</filename>
	<path>\\vmware-host\Shared Folders\Desktop\plates\18.jpg</path>
	<source>
		<database>Unknown</database>
	</source>
	<size>
		<width>200</width>
		<height>100</height>
		<depth>3</depth>
	</size>
	<segmented>0</segmented>
	<object>
		<name>T</name>
		<pose>Unspecified</pose>
		<truncated>0</truncated>
		<difficult>0</difficult>
		<bndbox>
			<xmin>38</xmin>
			<ymin>5</ymin>
			<xmax>63</xmax>
			<ymax>43</ymax>
		</bndbox>
	</object>
</annotation>
